rapid_elastic/__init__.py
rapid_elastic/cli.py
rapid_elastic/config.py
rapid_elastic/disease_icd10.py
rapid_elastic/disease_names.py
rapid_elastic/elastic_helper.py
rapid_elastic/filetool.py
rapid_elastic/kql_syntax.py
rapid_elastic/naming.py
rapid_elastic/pipeline.py
rapid_elastic/sql_compare.py
rapid_elastic/timestamp.py
rapid_elastic/resources/disease_names_expanded.json
rapid_elastic-1.0.1.dist-info/entry_points.txt
rapid_elastic-1.0.1.dist-info/licenses/LICENSE
rapid_elastic-1.0.1.dist-info/WHEEL
rapid_elastic-1.0.1.dist-info/METADATA
rapid_elastic-1.0.1.dist-info/RECORD
