Metadata-Version: 2.4
Name: rapid-elastic
Version: 1.0.1
Summary: Rapidly query clinical notes in Elasticsearch for mentions of diseases
Requires-Python: >= 3.10
Classifier: License :: OSI Approved :: Apache Software License
Classifier: Operating System :: OS Independent
Classifier: Programming Language :: Python :: 3
Classifier: Topic :: Software Development :: Libraries :: Python Modules
License-File: LICENSE
Requires-Dist: elasticsearch8
Requires-Dist: rich
Requires-Dist: pytest ; extra == "tests"
Requires-Dist: pytest-cov ; extra == "tests"
Project-URL: Homepage, https://github.com/smart-on-fhir/rapid-elastic
Provides-Extra: tests
